common_utils/common_utils.pyi
common_utils/__init__.py
common_utils/common_utils.abi3.so
huoniao_common-0.1.2.dist-info/METADATA
huoniao_common-0.1.2.dist-info/RECORD
huoniao_common-0.1.2.dist-info/top_level.txt
huoniao_common-0.1.2.dist-info/WHEEL
