Metadata-Version: 2.1
Name: huoniao_common
Version: 0.1.2
Summary: My short description for my project.
Home-page: https://github.com/shanyuwang/wsml
Author: huoniao
Author-email: me@example.com
License: MIT
Platform: all
Classifier: License :: OSI Approved :: BSD License
Classifier: Programming Language :: Python
Classifier: Programming Language :: Python :: 3
Classifier: Programming Language :: Python :: 3.8
Classifier: Programming Language :: Python :: Implementation :: CPython
Classifier: Programming Language :: Python :: Implementation :: PyPy
Classifier: Natural Language :: Chinese (Simplified)
Requires-Python: >=3.8.0
Requires-Dist: pyyaml
Requires-Dist: requests
Requires-Dist: nest-asyncio
Requires-Dist: anyio
